Workbook

Sheet Balance de situacion
C1: ACTIVOS | F1: PATRIMONIO NETO + PASIVOS
C2: A) ACTIVO NO CORRIENTE | D2: =D3+D4+D7+D8+D9+D10 -> 10000 | F2: A) PATRIMONIO NETO | G2: =G3+G14 -> 3000
C3: I. Inmovilizado intangible | D3: 0 | F3: A-1 FONDOS PROPIOS | G3: =G4+G5+G6+G9+G10+G11+G12+G13 -> 3000
C4: II. Inmovilizado material | D4: =D5+D6 -> 10000 | F4: I. Capital | G4: 0
C5: Terrenos y construcciones | D5: 0 | F5: II. Prima de emisión | G5: 0
C6: Instalaciones técnicas y otro inmovilizado material | D6: 10000 | F6: III. Reservas | G6: =G7+G8 -> 3000
C7: III. Inversiones inmobiliarias | D7: 0 | F7: Legales y estatutarias | G7: 3000
C8: IV. Inversiones en empresas del grupo y asociadas L.P. | D8: 0 | F8: Otras reservas | G8: 0
C9: V. Inversiones financieras a largo plazo | D9: 0 | F9: IV. Acciones y participaciones en patrimonio propias | G9: 0
C10: VI. Activos por impuesto diferido | D10: 0 | F10: V. Resultados de ejercicios anteriores | G10: 0
C11: B) ACTIVO CORRIENTE | D11: =D12+D15+D19+D20+D21+D22 -> 5000 | F11: VI. Otras aportaciones de socios | G11: 0
C12: I. Existencias | D12: =D13+D14 -> 0 | F12: VII. Resultado del ejercicio | G12: 0
C13: Comerciales | D13: 0 | F13: VIII. Dividendo a cuenta | G13: 0
C14: Productos en curso | D14: 0 | F14: A-2 SUBVENCIONES, DONACIONES Y LEGADOS | G14: 0
C15: II. Deudores comerciales y otras cuentas a cobrar | D15: =D16+D17+D18 -> 5000 | F15: B) PASIVO NO CORRIENTE | G15: =G16+G17+G18+G19+G20 -> 8000
C16: Clientes por ventas y otras prestaciones de servicios | D16: 5000 | F16: I. Provisiones a largo plazo | G16: 0
C17: Deudores varios | D17: 0 | F17: II. Deudas a largo plazo | G17: 8000
C18: Otros créditos con las administraciones Publicas | D18: 0 | F18: III Deudas con empresas del grupo y asociadas a L.P. | G18: 0
C19: III. Inversiones en empresas del grupo/asociadas C.P. | D19: 0 | F19: IV. Pasivos por impuesto diferido | G19: 0
C20: IV. Inversiones financieras a corto plazo | D20: 0 | F20: V. Periodificaciones a largo plazo | G20: 0
C21: V. Periodificaciones a corto plazo | D21: 0 | F21: C) PASIVO CORRIENTE | G21: =G23+G24+G25+G30 -> 4000
C22: VI. Efectivo y otros activos líquidos equivalentes | D22: 0 | F22: I. Provisiones a corto plazo | G22: 0
C23: TOTAL ACTIVO (A + B) | D23: =D2+D11 -> 15000 | F23: II. Deudas a corto plazo | G23: 1000
F24: III. Deudas con empresas del grupo y asociadas a C.P. | G24: 0
F25: IV. Acreedores a corto plazo y otras cuentas a pagar | G25: =G26+G27+G28+G29 -> 3000
F26: Proveedores a corto plazo | G26: 3000
F27: Acreedores varios | G27: 0
F28: Otras deudas con Administraciones Públicas | G28: 0
F29: Personal (remuneraciones pendientes de pago) | G29: 0
F30: V. Periodificaciones a corto plazo | G30: 0
F31: TOTAL P.NETO + PASIVOS (A + B + C) | G31: =G21+G15+G2 -> 15000
C35: Automatiza tu contabilidad con Holded. Empieza gratis.

Sheet Gráfico de balance de situación
A1: RESUMEN DEL BALANCE DE SITUACIÓN
B3: ACTIVO | D3: PASIVO
B4: ="Activo no corriente: "&A19 -> Activo no corriente: 10000 | D4: ="Patrimonio neto: "&B19 -> Patrimonio neto: 3000
B5: ="Activo corriente: "&A20 -> Activo corriente: 5000 | D5: ="Pasivo no corriente: "&B20 -> Pasivo no corriente: 8000
D6: ="Pasivo corriente: "&B21 -> Pasivo corriente: 4000
B7: ="Activo TOTAL:"&A22 -> Activo TOTAL:15000 | D7: ="Pasivo TOTAL: "&B22 -> Pasivo TOTAL: 15000
B9: =IF(A22=B22," ","ERROR!! ACTIVO Y PASIVO DEBEN SUMAR LO MISMO")
A10: Gráfico del balance de situación de tu empresa
A19: ='Balance de situacion'!D2 -> 10000 | B19: ='Balance de situacion'!G2 -> 3000
A20: ='Balance de situacion'!D11 -> 5000 | B20: ='Balance de situacion'!G15 -> 8000
B21: ='Balance de situacion'!G21 -> 4000
A22: =SUM(A19:A20) -> 15000 | B22: =SUM(B19:B21) -> 15000
